FoKL/Experimental_Embedded_GPs.py
FoKL/FoKLRoutines.py
FoKL/GP_Integrate.py
FoKL/JAX_Eval.py
FoKL/__init__.py
FoKL/fokl_to_pyomo.py
FoKL/getKernels.py
FoKL/kernels/orthogonal_Bn_scaled.txt
FoKL/kernels/splineCoefficient500_highPrecision_smoothed.txt
fokl-3.5.9.dist-info/licenses/LICENSE
fokl-3.5.9.dist-info/METADATA
fokl-3.5.9.dist-info/WHEEL
fokl-3.5.9.dist-info/top_level.txt
fokl-3.5.9.dist-info/RECORD
