Metadata-Version: 2.4
Name: FoKL
Version: 3.5.9
Summary: Karhunen Loève decomposed Gaussian processes with forward variable selection
Author-email: ESMS Group <derek.slack.001@gmail.com>
Classifier: Programming Language :: Python :: 3
Requires-Python: >=3.8
License-File: LICENSE
Requires-Dist: requests
Requires-Dist: importlib-metadata; python_version < "3.8"
Requires-Dist: NumPy
Requires-Dist: pandas
Requires-Dist: matplotlib
Provides-Extra: pyomo
Requires-Dist: Pyomo>=6.7.0; extra == "pyomo"
Requires-Dist: NumPy<2.0.0; extra == "pyomo"
Provides-Extra: jax
Requires-Dist: JAX; extra == "jax"
Dynamic: license-file
